altercase/__init__.py
altercase-0.1.0.dist-info/LICENSE
altercase-0.1.0.dist-info/METADATA
altercase-0.1.0.dist-info/WHEEL
altercase-0.1.0.dist-info/entry_points.txt
altercase-0.1.0.dist-info/top_level.txt
altercase-0.1.0.dist-info/RECORD
