Metadata-Version: 2.1
Name: altercase
Version: 0.1.0
Summary: Convert strings into different cases.
Author-email: Elmer Nocon <elmernocon@gmail.com>
License: MIT License
Classifier: Environment :: Console
Classifier: Intended Audience :: Developers
Classifier: License :: OSI Approved :: MIT License
Classifier: Operating System :: OS Independent
Classifier: Programming Language :: Python
Classifier: Programming Language :: Python :: 3.7
Classifier: Programming Language :: Python :: 3.8
Classifier: Programming Language :: Python :: 3.9
Classifier: Programming Language :: Python :: 3.10
Classifier: Programming Language :: Python :: 3.11
Classifier: Programming Language :: Python :: 3.12
Classifier: Programming Language :: Python :: 3.13
Classifier: Programming Language :: Python :: 3 :: Only
Classifier: Topic :: Software Development :: Libraries :: Python Modules
Requires-Python: >=3.7
License-File: LICENSE
Provides-Extra: dev
Requires-Dist: ruff ; extra == 'dev'
Provides-Extra: test
Requires-Dist: PyYAML ; extra == 'test'
